README.md
setup.py
nimport/__init__.py
nimport/magic_extension.py
nimport/utils.py
nimport.egg-info/PKG-INFO
nimport.egg-info/SOURCES.txt
nimport.egg-info/dependency_links.txt
nimport.egg-info/requires.txt
nimport.egg-info/top_level.txt
nimport/lib/__init__.py
nimport/lib/constants.py
nimport/lib/nimport_magic.py
nimport/lib/notebook.py
nimport/lib/parser.py
nimport/lib/tokens.py
nimport/providers/__init__.py
nimport/providers/constants.py
nimport/providers/github.py
nimport/providers/provider.py