Metadata-Version: 2.1
Name: nimport
Version: 0.10.17
Summary: A cool way to import notebooks into notebooks! Also can parameterize notebooks when it loads!
Home-page: https://github.com/yaananth/nimport
Author: Yash
Author-email: yashanantha@outlook.com
License: UNKNOWN
Platform: UNKNOWN
